{
  "Name": "Spruce Beer",
  "Description": "A carbonated drink made from spruce essence, it has an acquired, woodsy taste with many health benefits.",
  "Category": "ArtisanGoods",
  "Edibility": 150,
  "EdibleIsDrink": true,
    "EdibleBuffs":
    {
        "Farming": 0,
        "Fishing": 0,
        "Mining": 0,
        "Luck": 0,
        "Foraging": 2,
        "MaxStamina": 0,
        "MagnetRadius": 0,
        "Speed": 0,
        "Defense": 2,
        "Attack": 0,
        "Duration": 360,
    },
  "Price": 800,
  "IsColored": false,
  "Recipe": null,
  "GiftTastes": {
    "Love": ["Vincent", "Jas"],
  "Like": ["Abigail", "Alex", "Caroline", "Clint", "Demetrius", "Dwarf", "Elliott", "Emily", "Evelyn", "George", "Gus", "Haley", "Harvey", "Jodi", "Kent", "Leah", "Lewis", "Linus", "Marnie", "Maru", "Pam", "Penny", "Pierre", "Robin", "Sam", "Sandy", "Sebastian", "Shane", "Wizard"],
  "Dislike": ["Krobus", "Willy"],
  },"NameLocalization": { 
		// "es": "",
		"ko": "ê°€ë¬¸ë¹„ë‚˜ë¬´ ìˆ ",
        //"de": "",
        // "fr": "",
        // "hu": "",
        // "it": "",
        //"ja": "",
        //"pt": "",
        // "ru": "",
        // "tr": "",
        "zh": "äº‘æ‰å•¤é…’",
    },
    "DescriptionLocalization":
    {
        // "es": "",
        "ko": "ê°€ë¬¸ë¹„ë‚˜ë¬´ ì—ì„¼ìŠ¤ë¡œ ë§Œë“  íƒ„ì‚°ìŒë£Œ. ë‚˜ë¬´ í–¥ì´ ê·¸ìœ½í•˜ë©° ëª¸ì—ë„ ì¢‹ìŠµë‹ˆë‹¤.",
        //"de": "",
        // "fr": "",
        // "hu": "",
        // "it": "",
        //"ja": "",
        //"pt": "",
        // "ru": "",
        // "tr": "",
        "zh": "ä¸€ç§ç”±äº‘æ‰ç²¾ååˆ¶æˆçš„ç¢³é…¸é¥®æ–™ï¼Œå…·æœ‰å¾—å¤©ç‹¬åšçš„æœ¨è´¨é¦™å‘³ï¼Œæ®è¯´å¯¹å¥åº·æœ‰ç›Šã€.",
}
}